createadmin/__init__.py
createadmin/management/__init__.py
createadmin/management/commands/__init__.py
createadmin/management/commands/createadmin.py
createadmin-1.0.dist-info/LICENSE
createadmin-1.0.dist-info/METADATA
createadmin-1.0.dist-info/WHEEL
createadmin-1.0.dist-info/top_level.txt
createadmin-1.0.dist-info/RECORD
