Metadata-Version: 2.1
Name: createadmin
Version: 1.0
Summary: Create Default Admin Credentials in Django Admin.
Home-page: https://github.com/xB0t/createadmin
Author: xB0t
Author-email: ychaudhari124@gmail.com
Maintainer: xB0t
Maintainer-email: ychaudhari124@gmail.com
License: MIT
Keywords: django django_admin django_admin_default_credentials django-admin-custom-credentials devops deployment
Classifier: Environment :: Web Environment
Classifier: Framework :: Django
Classifier: License :: OSI Approved :: MIT License
Classifier: Operating System :: OS Independent
Classifier: Programming Language :: Python
Classifier: Programming Language :: Python :: 3
Classifier: Programming Language :: Python :: 3 :: Only
Classifier: Programming Language :: Python :: 3.10
Classifier: Topic :: Software Development :: Libraries :: Python Modules
License-File: LICENSE
